dnadamage/__init__.py
dnadamage/analysis.py
dnadamage/utils.py
tests/__init__.py
tests/test_analysis.py
DNAdamageclassifierDx-0.1.dist-info/LICENSE
DNAdamageclassifierDx-0.1.dist-info/METADATA
DNAdamageclassifierDx-0.1.dist-info/WHEEL
DNAdamageclassifierDx-0.1.dist-info/top_level.txt
DNAdamageclassifierDx-0.1.dist-info/RECORD
