Metadata-Version: 2.1
Name: DNAdamageclassifierDx
Version: 0.1
Summary: A package for analyzing DNA damage in COMET ASSAY images.
Home-page: https://github.com/yourusername/DNAdamageclassifierDx
Author: MD BABU MIA
Author-email: md.babu.mia@mssm.edu
Classifier: Programming Language :: Python :: 3
Classifier: License :: OSI Approved :: MIT License
Classifier: Operating System :: OS Independent
License-File: LICENSE
Requires-Dist: numpy
Requires-Dist: matplotlib
Requires-Dist: scikit-image
Requires-Dist: plotly
